[{"Warehouse":"00","Part No":"37348-128","Canadian Tire Part Number (UDF)":"6520536","Description":"FLORAL LIGHTS-WHITE BONSAI TREE AC-128LED","Sell 01":35,"Sell 03":0,"Status":0,"Inventory Type":"S","Available":134,"On Hand":134,"Backorder":6,"Committed":0,"On Order":0,"Product Code":"LED-TRE","Last Year Units":117,"This Year Units":210,"Next Year Units":79,"Last Sale Date":44182,"Last Receipt Date":44145,"Length (UDF)":22,"Width (UDF)":20,"Height (UDF)":32,"Created":40492.33403541666,"Modified":44146.63517431443,"Modified By":"WH","ImagePath":"Z:\\BV32\\IMAGES\\37348-128.JPG","UPC":"738362024241"},{"Warehouse":"00","Part No":"37367-128","Canadian Tire Part Number (UDF)":"6520537","Description":"FLORAL LIGHTS-PINK BONSAI TREE AC-128LED","Sell 01":35,"Sell 03":0,"Status":0,"Inventory Type":"S","Available":25,"On Hand":33,"Backorder":1,"Committed":8,"On Order":0,"Product Code":"LED-TRE","Last Year Units":108,"This Year Units":95,"Next Year Units":71,"Last Sale Date":44182,"Last Receipt Date":44145,"Length (UDF)":22,"Width (UDF)":20,"Height (UDF)":32,"Created":40660.48678622685,"Modified":44145.45834417142,"Modified By":"JH","ImagePath":"Z:\\BV32\\IMAGES\\37367-128.JPG","UPC":"738362025712"},{"Warehouse":"00","Part No":"37371-96","Canadian Tire Part Number (UDF)":"6520538","Description":"FLORAL LIGHTS-SILVER DOLLAR BONSAI TREE AC-96LED","Sell 01":37.5,"Sell 03":0,"Status":0,"Inventory Type":"S","Available":80,"On Hand":80,"Backorder":0,"Committed":0,"On Order":0,"Product Code":"LED-TRE","Last Year Units":98,"This Year Units":52,"Next Year Units":28,"Last Sale Date":44176,"Last Receipt Date":44119,"Length (UDF)":22,"Width (UDF)":20,"Height (UDF)":32,"Created":40864.44393078703,"Modified":44133.31802969177,"Modified By":"KON","ImagePath":"Z:\\BV32\\IMAGES\\37371-96.JPG","UPC":"738362027525"},{"Warehouse":"00","Part No":"37400","Canadian Tire Part Number (UDF)":"6520539","Description":"FLORAL LIGHTS-BONSAI TREE-INDOOR/OUTDOOR WARM WT AC 96 LED","Sell 01":25,"Sell 03":0,"Status":0,"Inventory Type":"S","Available":80,"On Hand":82,"Backorder":1,"Committed":2,"On Order":0,"Product Code":"LED-TRE","Last Year Units":172,"This Year Units":143,"Next Year Units":57,"Last Sale Date":44181,"Last Receipt Date":44123,"Length (UDF)":15,"Width (UDF)":15,"Height (UDF)":22,"Created":41407.32933449074,"Modified":44134.61842390909,"Modified By":"AG","ImagePath":"Z:\\BV32\\IMAGES\\37400.JPG","UPC":"738362035810"},{"Warehouse":"00","Part No":"37400-208-WT","Canadian Tire Part Number (UDF)":"6520540","Description":"FLORAL LIGHTS-OUTDOOR CHERRY TREE - 208 LED-INCL 6 GLIMMERING LIGHTS","Sell 01":45,"Sell 03":0,"Status":0,"Inventory Type":"S","Available":69,"On Hand":69,"Backorder":0,"Committed":0,"On Order":0,"Product Code":"LED-TRE","Last Year Units":104,"This Year Units":99,"Next Year Units":89,"Last Sale Date":44182,"Last Receipt Date":44145,"Length (UDF)":26,"Width (UDF)":26,"Height (UDF)":42.5,"Created":41989.5234712963,"Modified":44145.45834449958,"Modified By":"JH","ImagePath":"Z:\\BV32\\IMAGES\\37400-208-WT.JPG","UPC":"738362042955"},{"Warehouse":"00","Part No":"37400-PK","Canadian Tire Part Number (UDF)":"6590955","Description":"FLORAL LIGHTS-BONSAI TREE-INDOOR/OUTDOOR PINK AC","Sell 01":25,"Sell 03":0,"Status":0,"Inventory Type":"S","Available":94,"On Hand":106,"Backorder":0,"Committed":12,"On Order":0,"Product Code":"LED-TRE","Last Year Units":144,"This Year Units":133,"Next Year Units":43,"Last Sale Date":44182,"Last Receipt Date":44145,"Length (UDF)":15,"Width (UDF)":15,"Height (UDF)":22,"Created":41599.51669212963,"Modified":44154.45678973024,"Modified By":"WH","ImagePath":"Z:\\BV32\\IMAGES\\37400-PK.JPG","UPC":"738362039115"},{"Warehouse":"00","Part No":"37400-XL-WTRG","Canadian Tire Part Number (UDF)":"6520541","Description":"FLORAL LIGHTS-OUTDOOR TREE DUAL CLR WT/RGB 336LED(HI-LINE EXCL)","Sell 01":89,"Sell 03":0,"Status":0,"Inventory Type":"S","Available":2,"On Hand":2,"Backorder":1,"Committed":0,"On Order":0,"Product Code":"LED-TRE","Last Year Units":403,"This Year Units":329,"Next Year Units":402,"Last Sale Date":44179,"Last Receipt Date":44172,"Length (UDF)":19.7,"Width (UDF)":19.7,"Height (UDF)":63,"Created":42970.23329016204,"Modified":44172.66640559677,"Modified By":"KON","ImagePath":"Z:\\BV32\\IMAGES\\37400-XL-WTRG.JPG","UPC":"738362051599"},{"Warehouse":"00","Part No":"37400-XL-WTWW","Canadian Tire Part Number (UDF)":"6520542","Description":"FLORAL LIGHTS-OUTDOOR TREE DUAL CLR WT/WW 336LED (HI-LINE EXCLUSIVE)","Sell 01":89,"Sell 03":0,"Status":0,"Inventory Type":"S","Available":0,"On Hand":4,"Backorder":24,"Committed":4,"On Order":0,"Product Code":"LED-TRE","Last Year Units":122,"This Year Units":125,"Next Year Units":171,"Last Sale Date":44176,"Last Receipt Date":44174,"Length (UDF)":28,"Width (UDF)":28,"Height (UDF)":63,"Created":42718.38063148148,"Modified":44174.71647402317,"Modified By":"JH","ImagePath":"Z:\\BV32\\IMAGES\\37400-XL-WTWW.JPG","UPC":"738362051209"},{"Warehouse":"00","Part No":"37402-160","Canadian Tire Part Number (UDF)":"6520543","Description":"BIRCH TREES 160 LED INDOOR ONLY WHITE CABLE/WOOD BASE","Sell 01":145,"Sell 03":0,"Status":0,"Inventory Type":"S","Available":-6,"On Hand":-1,"Backorder":3,"Committed":5,"On Order":0,"Product Code":"LED-TRE","Last Year Units":147,"This Year Units":173,"Next Year Units":286,"Last Sale Date":44180,"Last Receipt Date":44174,"Length (UDF)":12,"Width (UDF)":12,"Height (UDF)":71,"Created":41436.40903668982,"Modified":44174.71647555033,"Modified By":"JH","ImagePath":"Z:\\BV32\\IMAGES\\37402-160.JPG","UPC":"738362036213"},{"Warehouse":"00","Part No":"37431-120","Canadian Tire Part Number (UDF)":"6520544","Description":"BIRCH TREE ON METAL BASE IN/OUTDOOR 120 LED 83 INCH HIGH","Sell 01":79,"Sell 03":0,"Status":0,"Inventory Type":"S","Available":-3,"On Hand":-6,"Backorder":29,"Committed":-3,"On Order":0,"Product Code":"LED-TRE","Last Year Units":772,"This Year Units":253,"Next Year Units":290,"Last Sale Date":44176,"Last Receipt Date":44145,"Length (UDF)":10,"Width (UDF)":10,"Height (UDF)":83,"Created":42515.30989282407,"Modified":44145.45834492386,"Modified By":"JH","ImagePath":"Z:\\BV32\\IMAGES\\37431-120.JPG","UPC":"738362049633"},{"Warehouse":"00","Part No":"37431-160","Canadian Tire Part Number (UDF)":"6520545","Description":"BIRCH TREE ON METAL BASE IN/OUTDOOR 160 LED 94 INCH HIGH","Sell 01":99,"Sell 03":0,"Status":0,"Inventory Type":"S","Available":34,"On Hand":35,"Backorder":0,"Committed":1,"On Order":0,"Product Code":"LED-TRE","Last Year Units":35,"This Year Units":66,"Next Year Units":64,"Last Sale Date":44182,"Last Receipt Date":44123,"Length (UDF)":23.62,"Width (UDF)":23.62,"Height (UDF)":94.5,"Created":43279.479003125,"Modified":44134.60786090761,"Modified By":"AG","ImagePath":"Z:\\BV32\\IMAGES\\37431-160.JPG","UPC":"738362054866"},{"Warehouse":"00","Part No":"37437-GD","Canadian Tire Part Number (UDF)":"6520555","Description":"FLORAL LIGHTS-WEEPING WILLOW BRANCHES WMWT 440LED/36FLASHING","Sell 01":45,"Sell 03":0,"Status":0,"Inventory Type":"S","Available":54,"On Hand":60,"Backorder":0,"Committed":6,"On Order":0,"Product Code":"LED-MIS","Last Year Units":60,"This Year Units":247,"Next Year Units":114,"Last Sale Date":44181,"Last Receipt Date":44119,"Length (UDF)":48,"Width (UDF)":0,"Height (UDF)":0,"Created":43091.26122905093,"Modified":44170.62904434872,"Modified By":"FC","ImagePath":"Z:\\BV32\\IMAGES\\37437-GD.JPG","UPC":"738362053845"},{"Warehouse":"00","Part No":"37438-GD","Canadian Tire Part Number (UDF)":"6520556","Description":"FLORAL LIGHTS-LED STARBURST WM WT 96 LED/12 FLASHING","Sell 01":20,"Sell 03":0,"Status":0,"Inventory Type":"S","Available":-1,"On Hand":6,"Backorder":42,"Committed":7,"On Order":0,"Product Code":"LED-MIS","Last Year Units":115,"This Year Units":347,"Next Year Units":666,"Last Sale Date":44154,"Last Receipt Date":44123,"Length (UDF)":15.75,"Width (UDF)":15.75,"Height (UDF)":15.75,"Created":43091.26151909722,"Modified":44123.45498718964,"Modified By":"JH","ImagePath":"Z:\\BV32\\IMAGES\\37438-GD.JPG","UPC":"738362053906"},{"Warehouse":"00","Part No":"37447-L","Canadian Tire Part Number (UDF)":"6520548","Description":"FLORAL LIGHTS-LARGE TREE W/288 WW LED PINK CHERRY BLOSSOM W/ADP","Sell 01":450,"Sell 03":0,"Status":0,"Inventory Type":"S","Available":2,"On Hand":2,"Backorder":0,"Committed":0,"On Order":0,"Product Code":"LED-TRE","Last Year Units":3,"This Year Units":7,"Next Year Units":0,"Last Sale Date":43880,"Last Receipt Date":43315,"Length (UDF)":70.87,"Width (UDF)":70.87,"Height (UDF)":98.5,"Created":43237.43233287037,"Modified":44117.46495713769,"Modified By":"AG","ImagePath":"Z:\\BV32\\IMAGES\\37447-L.JPG","UPC":"738362054361"},{"Warehouse":"00","Part No":"37447-M","Canadian Tire Part Number (UDF)":"6520547","Description":"FLORAL LIGHT-MED TREE W/84 WW LED PINK CHERRY BLOSSOM W/ADP","Sell 01":175,"Sell 03":0,"Status":0,"Inventory Type":"S","Available":31,"On Hand":31,"Backorder":0,"Committed":0,"On Order":0,"Product Code":"LED-TRE","Last Year Units":25,"This Year Units":29,"Next Year Units":10,"Last Sale Date":44176,"Last Receipt Date":44098,"Length (UDF)":35.4,"Width (UDF)":35.4,"Height (UDF)":70.86,"Created":43237.43638726852,"Modified":44133.31803816209,"Modified By":"KON","ImagePath":"Z:\\BV32\\IMAGES\\37447-M.JPG","UPC":"738362054385"},{"Warehouse":"00","Part No":"37447-S","Canadian Tire Part Number (UDF)":"6520546","Description":"FLORAL LIGHTS-SMALL TREE W/66 WW LED PINK CHERRY BLOSSOM W/ADP","Sell 01":99,"Sell 03":0,"Status":0,"Inventory Type":"S","Available":38,"On Hand":42,"Backorder":0,"Committed":4,"On Order":0,"Product Code":"LED-TRE","Last Year Units":26,"This Year Units":34,"Next Year Units":8,"Last Sale Date":44176,"Last Receipt Date":44098,"Length (UDF)":31.4,"Width (UDF)":31.4,"Height (UDF)":47.24,"Created":43237.43448391204,"Modified":44117.46390611916,"Modified By":"AG","ImagePath":"Z:\\BV32\\IMAGES\\37447-S.JPG","UPC":"738362054378"},{"Warehouse":"00","Part No":"37448-L","Canadian Tire Part Number (UDF)":"6520548","Description":"FLORAL LIGHTS-LARGE TREE W/138 WW LED RED ROSE W/ADP","Sell 01":199,"Sell 03":0,"Status":0,"Inventory Type":"S","Available":31,"On Hand":32,"Backorder":0,"Committed":1,"On Order":0,"Product Code":"LED-TRE","Last Year Units":0,"This Year Units":6,"Next Year Units":3,"Last Sale Date":44134,"Last Receipt Date":44119,"Length (UDF)":31.5,"Width (UDF)":31.5,"Height (UDF)":82.68,"Created":43600.36425462963,"Modified":44133.31803843949,"Modified By":"KON","ImagePath":"Z:\\BV32\\IMAGES\\37448-L.JPG","UPC":"738362056662"},{"Warehouse":"00","Part No":"37457-BR","Canadian Tire Part Number (UDF)":"6520549","Description":"FLORAL LIGHTS-BROWN TREE W/380 WW SPARKLING LED","Sell 01":79,"Sell 03":0,"Status":0,"Inventory Type":"S","Available":-2,"On Hand":1,"Backorder":0,"Committed":3,"On Order":0,"Product Code":"LED-TRE","Last Year Units":23,"This Year Units":59,"Next Year Units":143,"Last Sale Date":44176,"Last Receipt Date":44123,"Length (UDF)":25,"Width (UDF)":25,"Height (UDF)":53.15,"Created":43286.43466087963,"Modified":44134.60988430573,"Modified By":"AG","ImagePath":"Z:\\BV32\\IMAGES\\37457-BR.JPG","UPC":"738362055184"},{"Warehouse":"00","Part No":"37457-SL","Canadian Tire Part Number (UDF)":"6520550","Description":"FLORAL LIGHTS-SILVER TREE W/380 WT SPARKLING LED","Sell 01":79,"Sell 03":0,"Status":0,"Inventory Type":"S","Available":2,"On Hand":3,"Backorder":0,"Committed":1,"On Order":0,"Product Code":"LED-TRE","Last Year Units":34,"This Year Units":75,"Next Year Units":159,"Last Sale Date":44168,"Last Receipt Date":43760,"Length (UDF)":25,"Width (UDF)":25,"Height (UDF)":53.15,"Created":43286.43928194445,"Modified":44133.31804001316,"Modified By":"KON","ImagePath":"Z:\\BV32\\IMAGES\\37457-SL.JPG","UPC":"738362055191"},{"Warehouse":"00","Part No":"37458-WW","Canadian Tire Part Number (UDF)":"6520557","Description":"CLUSTER SNOWFLAKE LIGHT W/804 WW SPARKLING LED-34 INCH H","Sell 01":120,"Sell 03":0,"Status":0,"Inventory Type":"S","Available":0,"On Hand":0,"Backorder":5,"Committed":0,"On Order":0,"Product Code":"LED-MIS","Last Year Units":57,"This Year Units":91,"Next Year Units":113,"Last Sale Date":44162,"Last Receipt Date":44123,"Length (UDF)":32,"Width (UDF)":3,"Height (UDF)":34,"Created":43286.44672731482,"Modified":44148.47722856513,"Modified By":"WH","ImagePath":"Z:\\BV32\\IMAGES\\37458-WW.JPG","UPC":"738362055221"},{"Warehouse":"00","Part No":"37473-M","Canadian Tire Part Number (UDF)":"6520558","Description":"3D LED STAR-MEDIUM W/160 WW LED INDOOR/OUTDOOR","Sell 01":45,"Sell 03":45,"Status":0,"Inventory Type":"S","Available":33,"On Hand":34,"Backorder":0,"Committed":1,"On Order":0,"Product Code":"LED-MIS","Last Year Units":162,"This Year Units":76,"Next Year Units":96,"Last Sale Date":44180,"Last Receipt Date":44145,"Length (UDF)":22.83,"Width (UDF)":2.36,"Height (UDF)":22.83,"Created":42123.50191030093,"Modified":44153.60891880112,"Modified By":"WH","ImagePath":"Z:\\BV32\\IMAGES\\37473-M.JPG","UPC":"738362044119"},{"Warehouse":"00","Part No":"37473-S","Canadian Tire Part Number (UDF)":"6520559","Description":"3D LED STAR-SMALL W/60 WW LED INDOOR/OUTDOOR","Sell 01":24.95,"Sell 03":24.95,"Status":0,"Inventory Type":"S","Available":47,"On Hand":51,"Backorder":1,"Committed":4,"On Order":0,"Product Code":"LED-MIS","Last Year Units":179,"This Year Units":80,"Next Year Units":70,"Last Sale Date":44182,"Last Receipt Date":44145,"Length (UDF)":11.8,"Width (UDF)":2.36,"Height (UDF)":11.8,"Created":42123.49843125,"Modified":44145.45834514271,"Modified By":"JH","ImagePath":"Z:\\BV32\\IMAGES\\37473-S.JPG","UPC":"738362044102"},{"Warehouse":"00","Part No":"37501-25-LED","Canadian Tire Part Number (UDF)":"6520560","Description":"25 BULB LED STRING LIGHTS IN/OUTDOOR BULBS INCLUDED","Sell 01":52,"Sell 03":0,"Status":0,"Inventory Type":"S","Available":2150,"On Hand":2161,"Backorder":0,"Committed":11,"On Order":0,"Product Code":"LED-MIS","Last Year Units":0,"This Year Units":6,"Next Year Units":1022,"Last Sale Date":44180,"Last Receipt Date":44119,"Length (UDF)":0,"Width (UDF)":0,"Height (UDF)":0,"Created":43703.50650636574,"Modified":44148.67229414878,"Modified By":"JH","ImagePath":"Z:\\BV32\\IMAGES\\37501-25-LED.JPG","UPC":"738362057096"}]